{"data":[{"page":1,"pages":1,"total":13},[{"domain_id":"9101","domain_name":"Fakfak","domain_url":"https://fakfakkab.bps.go.id"},{"domain_id":"9102","domain_name":"Kaimana","domain_url":"https://kaimanakab.bps.go.id"},{"domain_id":"9103","domain_name":"Teluk Wondama","domain_url":"https://telukwondamakab.bps.go.id"},{"domain_id":"9104","domain_name":"Teluk Bintuni","domain_url":"https://telukbintunikab.bps.go.id"},{"domain_id":"9105","domain_name":"Manokwari","domain_url":"https://manokwarikab.bps.go.id"},{"domain_id":"9106","domain_name":"Sorong Selatan","domain_url":"https://sorongselatankab.bps.go.id"},{"domain_id":"9107","domain_name":"Sorong","domain_url":"https://sorongkab.bps.go.id"},{"domain_id":"9108","domain_name":"Raja Ampat","domain_url":"https://rajaampatkab.bps.go.id"},{"domain_id":"9109","domain_name":"Tambrauw","domain_url":"https://tambrauwkab.bps.go.id"},{"domain_id":"9110","domain_name":"Maybrat","domain_url":"https://maybratkab.bps.go.id"},{"domain_id":"9111","domain_name":"Manokwari Selatan","domain_url":"https://manokwariselatankab.bps.go.id"},{"domain_id":"9112","domain_name":"Pegunungan Arfak","domain_url":"https://pegununganarfakkab.bps.go.id"},{"domain_id":"9171","domain_name":"Sorong","domain_url":"https://sorongkota.bps.go.id"}]],"data-availability":"available","status":"OK"}